mverb3/__init__.py
mverb3/__main__.py
mverb3/app.py
mverb3/bank.py
mverb3/ui/__init__.py
mverb3/ui/about.py
mverb3/ui/main.py
mverb3/ui/settings.py
midiverb3-1.0.5.dist-info/LICENSE
midiverb3-1.0.5.dist-info/METADATA
midiverb3-1.0.5.dist-info/WHEEL
midiverb3-1.0.5.dist-info/entry_points.txt
midiverb3-1.0.5.dist-info/top_level.txt
midiverb3-1.0.5.dist-info/RECORD
