Metadata-Version: 2.1
Name: midiverb3
Version: 1.0.5
Summary: Alesis MidiVerb III editor
Author-email: violet-black <violetblackdev@gmail.com>
Project-URL: Homepage, https://github.com/violet-black/midiverb3
Keywords: reverb,music
Classifier: Development Status :: 4 - Beta
Classifier: Programming Language :: Python
Classifier: License :: OSI Approved :: MIT License
Requires-Python: >=3.8
License-File: LICENSE
Requires-Dist: pyside6
Requires-Dist: python-rtmidi<2
